redis_lock/__init__.py
redis_lock/base.py
redis_lock/exceptions.py
redis_lock/lock.py
redis_lock/py.typed
redis_lock/spin_lock.py
redis_lock/types.py
redis_lock/asyncio/__init__.py
redis_lock/asyncio/async_lock.py
redis_lock/asyncio/base.py
redis_lock/asyncio/py.typed
sfmario_redis_lock_py-1.2.2.dist-info/METADATA
sfmario_redis_lock_py-1.2.2.dist-info/WHEEL
sfmario_redis_lock_py-1.2.2.dist-info/licenses/LICENSE
sfmario_redis_lock_py-1.2.2.dist-info/RECORD
