Metadata-Version: 2.4
Name: sfmario-redis-lock-py
Version: 1.2.2
Summary: Fork of redis-lock-py with asyncio types
Project-URL: Homepage, https://github.com/miintto/redis-lock-py
Author-email: Minjae Park <miintto.log@gmail.com>, Mario Martin <24687973+Mariomm-marti@users.noreply.github.com>
License-Expression: MIT
License-File: LICENSE
Classifier: Development Status :: 5 - Production/Stable
Classifier: License :: OSI Approved :: MIT License
Classifier: Programming Language :: Python :: 3
Classifier: Programming Language :: Python :: 3.9
Classifier: Programming Language :: Python :: 3.10
Classifier: Programming Language :: Python :: 3.11
Classifier: Programming Language :: Python :: 3.12
Classifier: Programming Language :: Python :: 3.13
Requires-Python: >=3.9
Requires-Dist: redis>=5.2.0
Provides-Extra: dev
Requires-Dist: mypy>=1.16.1; extra == 'dev'
Provides-Extra: test
Requires-Dist: coverage==7.1.0; extra == 'test'
Requires-Dist: pytest-asyncio==0.20.3; extra == 'test'
Requires-Dist: pytest==7.2.1; extra == 'test'
